xnotify/__init__.py
xnotify/__main__.py
xnotify/__version__.py
xnotify/cli.py
xnotify/client.py
xnotify/config.py
xnotify/core.py
xnotify/custom_logging.py
xnotify/logger.py
xnotify/server.py
xnotify/utils.py
xnotify/plugins/__init__.py
xnotify/plugins/base.py
xnotify/plugins/discord.py
xnotify/plugins/growl.py
xnotify/plugins/ntfy.py
xnotify/plugins/pushbullet.py
xnotify/plugins/pushover.py
xnotify/plugins/slack.py
xnotify/plugins/syslog.py
xnotify/plugins/telegram.py
xnotify-3.0.5.dist-info/licenses/LICENSE
xnotify-3.0.5.dist-info/METADATA
xnotify-3.0.5.dist-info/WHEEL
xnotify-3.0.5.dist-info/entry_points.txt
xnotify-3.0.5.dist-info/top_level.txt
xnotify-3.0.5.dist-info/RECORD
