Metadata-Version: 2.4
Name: xnotify
Version: 3.0.5
Summary: Universal notification library with plugin support
Home-page: https://github.com/cumulus13/xnotify
Author: cumulus13
Author-email: Hadi Cahyadi <cumulus13@gmail.com>
License: MIT
Project-URL: Homepage, https://github.com/cumulus13/xnotify
Project-URL: Documentation, https://github.com/cumulus13/xnotify#readme
Project-URL: Repository, https://github.com/cumulus13/xnotify
Project-URL: Bug Tracker, https://github.com/cumulus13/xnotify/issues
Keywords: notification,pushbullet,ntfy,pushover,telegram,discord,slack,alert,monitoring
Classifier: Development Status :: 4 - Beta
Classifier: Intended Audience :: Developers
Classifier: Programming Language :: Python :: 3
Classifier: Programming Language :: Python :: 3.7
Classifier: Programming Language :: Python :: 3.8
Classifier: Programming Language :: Python :: 3.9
Classifier: Programming Language :: Python :: 3.10
Classifier: Programming Language :: Python :: 3.11
Classifier: Programming Language :: Python :: 3.12
Classifier: Operating System :: OS Independent
Requires-Python: >=3.7
License-File: LICENSE
Requires-Dist: progress_session>=0.30.2
Requires-Dist: gntplib>=3.0.0
Requires-Dist: pyyaml>=5.4.0
Provides-Extra: full
Requires-Dist: pushbullet.py>=0.12.0; extra == "full"
Requires-Dist: pyyaml>=5.4.0; extra == "full"
Requires-Dist: progress_session>=0.30.2; extra == "full"
Requires-Dist: gntplib>=3.0.0; extra == "full"
Requires-Dist: licface; extra == "full"
Requires-Dist: richcolorlog>=1.0.0; extra == "full"
Provides-Extra: yaml
Requires-Dist: pyyaml>=5.4.0; extra == "yaml"
Provides-Extra: growl
Requires-Dist: gntplib>=3.0.0; extra == "growl"
Provides-Extra: pushbullet
Requires-Dist: pushbullet.py>=0.12.0; extra == "pushbullet"
Provides-Extra: ntfy
Requires-Dist: progress_session>=0.30.2; extra == "ntfy"
Provides-Extra: log
Requires-Dist: richcolorlog>=1.0.0; extra == "log"
Requires-Dist: licface; extra == "log"
Provides-Extra: dev
Requires-Dist: pytest>=7.0.0; extra == "dev"
Requires-Dist: pytest-cov>=3.0.0; extra == "dev"
Requires-Dist: black>=22.0.0; extra == "dev"
Requires-Dist: flake8>=4.0.0; extra == "dev"
Requires-Dist: mypy>=0.950; extra == "dev"
Requires-Dist: isort>=5.10.0; extra == "dev"
Requires-Dist: licface; extra == "dev"
Requires-Dist: richcolorlog>=1.0.0; extra == "dev"
Dynamic: author
Dynamic: home-page
Dynamic: license-file
Dynamic: requires-python
